Metadata-Version: 2.1
Name: distributions-fitting-v001
Version: 0.1
Summary: Gaussian distributions
Home-page: UNKNOWN
License: UNKNOWN
Platform: UNKNOWN
License-File: license.txt
